MANIFEST.in
README.rst
setup.py
generic_oauth/__init__.py
generic_oauth.egg-info/PKG-INFO
generic_oauth.egg-info/SOURCES.txt
generic_oauth.egg-info/dependency_links.txt
generic_oauth.egg-info/requires.txt
generic_oauth.egg-info/top_level.txt