Metadata-Version: 1.1
Name: generic-oauth
Version: 0.1
Summary: generic_oauth makes it extremely simple to use any OAuth v2 API purely from the command line.
Home-page: http://github.com/vivekseth/generic_oauth
Author: Vivek Seth
Author-email: viveksethm@example.com
License: MIT
Keywords: oauth api google facebook spotify github
Platform: UNKNOWN
Classifier: Development Status :: 3 - Alpha
Classifier: License :: OSI Approved :: MIT License
Classifier: Programming Language :: Python :: 2.7
